ggeocoder.py
ggeocoder-2.0.0.dist-info/LICENSE
ggeocoder-2.0.0.dist-info/METADATA
ggeocoder-2.0.0.dist-info/WHEEL
ggeocoder-2.0.0.dist-info/top_level.txt
ggeocoder-2.0.0.dist-info/RECORD
