Metadata-Version: 2.1
Name: ggeocoder
Version: 2.0.0
Summary: A Python library for working with Google Geocoding API V3.
Home-page: https://github.com/imtapps/ggeocoder
Author: Aaron Madison
License: BSD License
Keywords: google maps api v3 geocode geocoding geocoder reverse
Classifier: Development Status :: 5 - Production/Stable
Classifier: Intended Audience :: Developers
Classifier: Natural Language :: English
Classifier: Operating System :: OS Independent
Classifier: Programming Language :: Python :: 2.7
Classifier: Programming Language :: Python :: 3.4
Classifier: Programming Language :: Python :: 3.5
Classifier: Programming Language :: Python :: 3.6
Classifier: Programming Language :: Python :: 3.7
Classifier: License :: OSI Approved :: BSD License
Classifier: Topic :: Internet
Classifier: Topic :: Internet :: WWW/HTTP
Classifier: Topic :: Scientific/Engineering :: GIS
Classifier: Topic :: Software Development :: Libraries :: Python Modules
Provides: ggeocoder
License-File: LICENSE
